{
 "actions": [],
 "allow_rename": 1,
 "creation": "2022-12-07 13:30:37.826482",
 "doctype": "DocType",
 "editable_grid": 1,
 "engine": "InnoDB",
 "field_order": [
  "start_day",
  "end_day"
 ],
 "fields": [
  {
   "fieldname": "start_day",
   "fieldtype": "Date",
   "label": "Start Day"
  },
  {
   "fieldname": "end_day",
   "fieldtype": "Date",
   "label": "End Day"
  }
 ],
 "index_web_pages_for_search": 1,
 "istable": 1,
 "links": [],
 "modified": "2024-10-27 11:28:54.843806",
 "modified_by": "Administrator",
 "module": "Patient Management",
 "name": "Days Period",
 "owner": "Administrator",
 "permissions": [],
 "sort_field": "modified",
 "sort_order": "DESC",
 "states": []
}